build/lib/build/lib/build/lib/mlx_whisper/__init__.py
build/lib/build/lib/build/lib/mlx_whisper/_version.py
build/lib/build/lib/build/lib/mlx_whisper/audio.py
build/lib/build/lib/build/lib/mlx_whisper/cli.py
build/lib/build/lib/build/lib/mlx_whisper/decoding.py
build/lib/build/lib/build/lib/mlx_whisper/load_models.py
build/lib/build/lib/build/lib/mlx_whisper/timing.py
build/lib/build/lib/build/lib/mlx_whisper/tokenizer.py
build/lib/build/lib/build/lib/mlx_whisper/torch_whisper.py
build/lib/build/lib/build/lib/mlx_whisper/transcribe.py
build/lib/build/lib/build/lib/mlx_whisper/version.py
build/lib/build/lib/build/lib/mlx_whisper/whisper.py
build/lib/build/lib/build/lib/mlx_whisper/writers.py
build/lib/build/lib/mlx_whisper/__init__.py
build/lib/build/lib/mlx_whisper/_version.py
build/lib/build/lib/mlx_whisper/audio.py
build/lib/build/lib/mlx_whisper/cli.py
build/lib/build/lib/mlx_whisper/decoding.py
build/lib/build/lib/mlx_whisper/load_models.py
build/lib/build/lib/mlx_whisper/timing.py
build/lib/build/lib/mlx_whisper/tokenizer.py
build/lib/build/lib/mlx_whisper/torch_whisper.py
build/lib/build/lib/mlx_whisper/transcribe.py
build/lib/build/lib/mlx_whisper/version.py
build/lib/build/lib/mlx_whisper/whisper.py
build/lib/build/lib/mlx_whisper/writers.py
build/lib/mlx_whisper/__init__.py
build/lib/mlx_whisper/_version.py
build/lib/mlx_whisper/audio.py
build/lib/mlx_whisper/cli.py
build/lib/mlx_whisper/decoding.py
build/lib/mlx_whisper/load_models.py
build/lib/mlx_whisper/timing.py
build/lib/mlx_whisper/tokenizer.py
build/lib/mlx_whisper/torch_whisper.py
build/lib/mlx_whisper/transcribe.py
build/lib/mlx_whisper/version.py
build/lib/mlx_whisper/whisper.py
build/lib/mlx_whisper/writers.py
mlx_whisper/__init__.py
mlx_whisper/_version.py
mlx_whisper/audio.py
mlx_whisper/cli.py
mlx_whisper/decoding.py
mlx_whisper/load_models.py
mlx_whisper/requirements.txt
mlx_whisper/timing.py
mlx_whisper/tokenizer.py
mlx_whisper/torch_whisper.py
mlx_whisper/transcribe.py
mlx_whisper-0.4.3.dist-info/METADATA
mlx_whisper-0.4.3.dist-info/WHEEL
mlx_whisper-0.4.3.dist-info/entry_points.txt
mlx_whisper-0.4.3.dist-info/top_level.txt
mlx_whisper-0.4.3.dist-info/RECORD
