Metadata-Version: 2.4
Name: mlx-whisper
Version: 0.4.3
Summary: OpenAI Whisper on Apple silicon with MLX and the Hugging Face Hub
Home-page: https://github.com/ml-explore/mlx-examples
Author: MLX Contributors
Author-email: mlx@group.apple.com
License: MIT
Requires-Python: >=3.8
Requires-Dist: mlx>=0.11
Requires-Dist: numba
Requires-Dist: numpy
Requires-Dist: torch
Requires-Dist: tqdm
Requires-Dist: more-itertools
Requires-Dist: tiktoken
Requires-Dist: huggingface_hub
Requires-Dist: scipy
Dynamic: author
Dynamic: author-email
Dynamic: description
Dynamic: description-content-type
Dynamic: home-page
Dynamic: license
Dynamic: requires-dist
Dynamic: requires-python
Dynamic: summary
